test_for_travis/__init__.py
test_for_travis/test_init.py
test_for_travis-0.1.dist-info/DESCRIPTION.rst
test_for_travis-0.1.dist-info/METADATA
test_for_travis-0.1.dist-info/RECORD
test_for_travis-0.1.dist-info/WHEEL
test_for_travis-0.1.dist-info/entry_points.txt
test_for_travis-0.1.dist-info/metadata.json
test_for_travis-0.1.dist-info/top_level.txt
