Metadata-Version: 2.0
Name: test-for-travis
Version: 0.1
Summary: test how to submit a project to pypi and test how to use the travis
Home-page: https://testupload.test
Author: wph
Author-email: wangpenghui@gene.ac
License: UNKNOWN
Platform: UNKNOWN
